xero/__init__.py
xero/api.py
xero/auth.py
xero/basemanager.py
xero/constants.py
xero/exceptions.py
xero/filesmanager.py
xero/manager.py
xero/payrollmanager.py
xero/utils.py
intellihr_pyxero-0.0.2.dist-info/LICENSE
intellihr_pyxero-0.0.2.dist-info/METADATA
intellihr_pyxero-0.0.2.dist-info/WHEEL
intellihr_pyxero-0.0.2.dist-info/top_level.txt
intellihr_pyxero-0.0.2.dist-info/RECORD
