Metadata-Version: 2.1
Name: intellihr-pyxero
Version: 0.0.2
Summary: Python API for accessing the REST API of the Xero accounting tool.
Home-page: http://github.com/freakboy3742/pyxero
Author: Russell Keith-Magee
Author-email: russell@keith-magee.com
License: New BSD
Platform: UNKNOWN
Classifier: Development Status :: 4 - Beta
Classifier: Environment :: Web Environment
Classifier: Intended Audience :: Financial and Insurance Industry
Classifier: License :: OSI Approved :: BSD License
Classifier: Operating System :: OS Independent
Classifier: Programming Language :: Python
Classifier: Programming Language :: Python :: 2.7
Classifier: Programming Language :: Python :: 3.4
Classifier: Programming Language :: Python :: 3.5
Classifier: Programming Language :: Python :: 3.6
Classifier: Programming Language :: Python :: 3.7
Classifier: Topic :: Office/Business :: Financial :: Accounting
Requires-Dist: six (>=1.8.0)
Requires-Dist: requests (>=1.1.0)
Requires-Dist: requests-oauthlib (>=0.3.0)
Requires-Dist: python-dateutil (>=2.1)
Requires-Dist: PyJWT (>=1.6.4)
Requires-Dist: cryptography (>=1.3.1)
